pythondata_cpu_ibex/__init__.py
pythondata_cpu_ibex/system_verilog/.clang-format
pythondata_cpu_ibex/system_verilog/.gitignore
pythondata_cpu_ibex/system_verilog/.svlint.toml
pythondata_cpu_ibex/system_verilog/CONTRIBUTING.md
pythondata_cpu_ibex/system_verilog/CREDITS.md
pythondata_cpu_ibex/system_verilog/LICENSE
pythondata_cpu_ibex/system_verilog/Makefile
pythondata_cpu_ibex/system_verilog/README.md
pythondata_cpu_ibex/system_verilog/azure-pipelines.yml
pythondata_cpu_ibex/system_verilog/check_tool_requirements.core
pythondata_cpu_ibex/system_verilog/ibex_configs.yaml
pythondata_cpu_ibex/system_verilog/ibex_core.core
pythondata_cpu_ibex/system_verilog/ibex_icache.core
pythondata_cpu_ibex/system_verilog/ibex_multdiv.core
pythondata_cpu_ibex/system_verilog/ibex_pkg.core
pythondata_cpu_ibex/system_verilog/ibex_top.core
pythondata_cpu_ibex/system_verilog/ibex_top_tracing.core
pythondata_cpu_ibex/system_verilog/ibex_tracer.core
pythondata_cpu_ibex/system_verilog/python-requirements.txt
pythondata_cpu_ibex/system_verilog/src_files.yml
pythondata_cpu_ibex/system_verilog/tool_requirements.py
pythondata_cpu_ibex/system_verilog/.github/ISSUE_TEMPLATE/bug.md
pythondata_cpu_ibex/system_verilog/.github/ISSUE_TEMPLATE/question.md
pythondata_cpu_ibex/system_verilog/.github/workflows/pr_lint_review.yml
pythondata_cpu_ibex/system_verilog/.github/workflows/pr_trigger.yml
pythondata_cpu_ibex/system_verilog/ci/azp-private.yml
pythondata_cpu_ibex/system_verilog/ci/ibex-rtl-ci-steps.yml
pythondata_cpu_ibex/system_verilog/ci/install-build-deps.sh
pythondata_cpu_ibex/system_verilog/ci/vars.yml
pythondata_cpu_ibex/system_verilog/ci/vars_to_logging_cmd.py
pythondata_cpu_ibex/system_verilog/doc/.gitignore
pythondata_cpu_ibex/system_verilog/doc/Makefile
pythondata_cpu_ibex/system_verilog/doc/conf.py
pythondata_cpu_ibex/system_verilog/doc/index.rst
pythondata_cpu_ibex/system_verilog/doc/make.bat
pythondata_cpu_ibex/system_verilog/doc/requirements.txt
pythondata_cpu_ibex-0.0.post2218.dist-info/LICENSE
pythondata_cpu_ibex-0.0.post2218.dist-info/METADATA
pythondata_cpu_ibex-0.0.post2218.dist-info/WHEEL
pythondata_cpu_ibex-0.0.post2218.dist-info/top_level.txt
pythondata_cpu_ibex-0.0.post2218.dist-info/RECORD
