Metadata-Version: 2.1
Name: pythondata-cpu-ibex
Version: 0.0.post2218
Summary: Python module containing system_verilog files for Ibex cpu.
Home-page: https://github.com/litex-hub/pythondata-cpu-ibex
Author: LiteX Authors
Author-email: litex@googlegroups.com
License: UNKNOWN
Project-URL: Bug Tracker, https://github.com/litex-hub/pythondata-cpu-ibex/issues
Project-URL: Source Code, https://github.com/litex-hub/pythondata-cpu-ibex
Platform: UNKNOWN
Classifier: Programming Language :: Python :: 3
Classifier: License :: OSI Approved :: Apache Software License
Classifier: Operating System :: OS Independent
Requires-Python: >=3.5
